pymortar/__init__.py
pymortar/application.py
pymortar/mortar_pb2.py
pymortar/mortar_pb2_grpc.py
pymortar-2.0.8.dist-info/WHEEL
pymortar-2.0.8.dist-info/METADATA
pymortar-2.0.8.dist-info/RECORD
